{"status":"ok","message-type":"work-list","message-version":"1.0.0","message":{"facets":{},"total-results":417,"items":[{"DOI":"10.35542\/osf.io\/hc2dw","title":["Making Data Science Count In and For Education"],"author":[{"ORCID":"https:\/\/orcid.org\/0000-0003-2170-0447","authenticated-orcid":true,"given":"Joshua","family":"Rosenberg","sequence":"first","affiliation":[]},{"given":"Michael","family":"Lawson","sequence":"additional","affiliation":[]},{"ORCID":"https:\/\/orcid.org\/0000-0003-4699-4680","authenticated-orcid":true,"given":"Daniel","family":"Anderson","sequence":"additional","affiliation":[]},{"given":"Ryan Seth","family":"Jones","sequence":"additional","affiliation":[]},{"ORCID":"https:\/\/orcid.org\/0000-0001-7978-2532","authenticated-orcid":true,"given":"Teomara","family":"Rutherford","sequence":"additional","affiliation":[]}],"issued":{"date-parts":[[2019,9,13]]},"URL":"https:\/\/doi.org\/10.35542\/osf.io\/hc2dw","type":"posted-content","publisher":"Center for Open Science"},{"publisher":"Routledge","DOI":"10.4324\/9780429260919-7","type":"book-chapter","page":"94-110","title":["Making Data Science Count In and For Education"],"author":[{"given":"Joshua M.","family":"Rosenberg","sequence":"first","affiliation":[]},{"given":"Michael","family":"Lawson","sequence":"additional","affiliation":[]},{"given":"Daniel J.","family":"Anderson","sequence":"additional","affiliation":[]},{"given":"Ryan Seth","family":"Jones","sequence":"additional","affiliation":[]},{"given":"Teomara","family":"Rutherford","sequence":"additional","affiliation":[]}],"container-title":["Research Methods in Learning Design and Technology"],"issued":{"date-parts":[[2020,9,11]]},"URL":"https:\/\/doi.org\/10.4324\/9780429260919-7"},{"publisher":"Routledge","DOI":"10.4324\/9780367822842-3","type":"book-chapter","page":"13-20","title":["What does data science in education look like?"],"author":[{"given":"Ryan A.","family":"Estrellado","sequence":"first","affiliation":[]},{"given":"Emily A.","family":"Freer","sequence":"additional","affiliation":[]},{"given":"Jesse","family":"Mostipak","sequence":"additional","affiliation":[]},{"given":"Joshua M.","family":"Rosenberg","sequence":"additional","affiliation":[]},{"given":"Isabella C.","family":"Vel\u00e1squez","sequence":"additional","affiliation":[]}],"container-title":["Data Science in Education Using R"],"issued":{"date-parts":[[2020,10,26]]},"URL":"https:\/\/doi.org\/10.4324\/9780367822842-3"},{"publisher":"Routledge","DOI":"10.4324\/9780367822842-15","type":"book-chapter","page":"229-240","title":["Introducing data science tools to your education job"],"author":[{"given":"Ryan A.","family":"Estrellado","sequence":"first","affiliation":[]},{"given":"Emily A.","family":"Freer","sequence":"additional","affiliation":[]},{"given":"Jesse","family":"Mostipak","sequence":"additional","affiliation":[]},{"given":"Joshua M.","family":"Rosenberg","sequence":"additional","affiliation":[]},{"given":"Isabella C.","family":"Vel\u00e1squez","sequence":"additional","affiliation":[]}],"container-title":["Data Science in Education Using R"],"issued":{"date-parts":[[2020,10,26]]},"URL":"https:\/\/doi.org\/10.4324\/9780367822842-15"},{"publisher":"Routledge","DOI":"10.4324\/9780367822842-16","type":"book-chapter","page":"241-249","title":["Teaching data science"],"author":[{"given":"Ryan A.","family":"Estrellado","sequence":"first","affiliation":[]},{"given":"Emily A.","family":"Freer","sequence":"additional","affiliation":[]},{"given":"Jesse","family":"Mostipak","sequence":"additional","affiliation":[]},{"given":"Joshua M.","family":"Rosenberg","sequence":"additional","affiliation":[]},{"given":"Isabella C.","family":"Vel\u00e1squez","sequence":"additional","affiliation":[]}],"container-title":["Data Science in Education Using R"],"issued":{"date-parts":[[2020,10,26]]},"URL":"https:\/\/doi.org\/10.4324\/9780367822842-16"}],"items-per-page":5,"query":{"start-index":0,"search-terms":null}}}
